pynq_emulator/__init__.py
pynq_emulator/emulation.py
pynq_emulator-2019.9.8.dist-info/LICENCE.txt
pynq_emulator-2019.9.8.dist-info/METADATA
pynq_emulator-2019.9.8.dist-info/WHEEL
pynq_emulator-2019.9.8.dist-info/top_level.txt
pynq_emulator-2019.9.8.dist-info/zip-safe
pynq_emulator-2019.9.8.dist-info/RECORD
